<?xml version='1.0' encoding='UTF-8'?>
<MixxxControllerPreset schemaVersion="1" mixxxVersion="2.0.0+">
  <info>
    <name>VDJC 1.0.0 </name>
    <author>Deja1987 &amp; AMI</author>
    <description>XML generato da Excel</description>
  </info>
  <controller id="VDJC MIDI Controller">
    <scriptfiles>
      <file filename="InitShutFunctions.js"/>
      <file filename="lodash.mixxx.js"/>
      <file filename="midi-components-0.2.js"/>
      <file functionprefix="VDJC" filename="VDJC_1.0.0-script.js"/>
    </scriptfiles>
    <controls>
      <control>
        <group>[Channel1]</group>
        <key>VDJC.pregainEncoderE</key>
        <status>0xB0</status>
        <midino>0x00</midino>
        <options>
          <Script-Binding/>
        </options>
      </control>
      <control>
        <group>[EqualizerRack1_[Channel1]_Effect1]</group>
        <key>VDJC.highEncoderE</key>
        <status>0xB0</status>
        <midino>0x01</midino>
        <options>
          <Script-Binding/>
        </options>
      </control>
      <control>
        <group>[EqualizerRack1_[Channel1]_Effect1]</group>
        <key>VDJC.midEncoderE</key>
        <status>0xB0</status>
        <midino>0x02</midino>
        <options>
          <Script-Binding/>
        </options>
      </control>
      <control>
        <group>[EqualizerRack1_[Channel1]_Effect1]</group>
        <key>VDJC.lowEncoderE</key>
        <status>0xB0</status>
        <midino>0x03</midino>
        <options>
          <Script-Binding/>
        </options>
      </control>
      <control> <!-- QuickEffect Preset Selector -->
        <group>[QuickEffectRack1_[Channel1]]</group>
        <key>VDJC.quickEffectPreset</key>
        <status>0xB0</status>
        <midino>0x04</midino>
        <options>
          <Script-Binding/>
        </options>
      </control>
      <control> <!-- EQ High Kill Button -->
        <group>[EqualizerRack1_[Channel1]_Effect1]</group>
        <key>VDJC.EQHighKillB</key>
        <status>0x90</status>
        <midino>0x06</midino>
        <options>
          <Script-Binding/>
        </options>
      </control>
      <control> <!-- EQ Mid Kill Button -->
        <group>[EqualizerRack1_[Channel1]_Effect1]</group>
        <key>VDJC.EQMidKillB</key>
        <status>0x90</status>
        <midino>0x07</midino>
        <options>
          <Script-Binding/>
        </options>
      </control>
      <control> <!-- EQ Low Kill Button -->
        <group>[EqualizerRack1_[Channel1]_Effect1]</group>
        <key>VDJC.EQLowKillB</key>
        <status>0x90</status>
        <midino>0x08</midino>
        <options>
          <Script-Binding/>
        </options>
      </control>
      <control> <!-- Quick Effect Enable Button -->
        <group>[QuickEffectRack1_[Channel1]]</group>
        <key>VDJC.QuickEffB</key>
        <status>0x90</status>
        <midino>0x09</midino>
        <options>
          <Script-Binding/>
        </options>
      </control>
      <control> <!-- EQ High Kill Button -->
        <group>[EqualizerRack1_[Channel2]_Effect1]</group>
        <key>VDJC.EQHighKillB</key>
        <status>0x91</status>
        <midino>0x06</midino>
        <options>
          <Script-Binding/>
        </options>
      </control>
      <control> <!-- EQ Mid Kill Button -->
        <group>[EqualizerRack1_[Channel2]_Effect1]</group>
        <key>VDJC.EQMidKillB</key>
        <status>0x91</status>
        <midino>0x07</midino>
        <options>
          <Script-Binding/>
        </options>
      </control>
      <control> <!-- EQ Low Kill Button -->
        <group>[EqualizerRack1_[Channel2]_Effect1]</group>
        <key>VDJC.EQLowKillB</key>
        <status>0x91</status>
        <midino>0x08</midino>
        <options>
          <Script-Binding/>
        </options>
      </control>
      <control> <!-- Quick Effect Enable Button -->
        <group>[QuickEffectRack1_[Channel2]]</group>
        <key>VDJC.QuickEffB</key>
        <status>0x91</status>
        <midino>0x09</midino>
        <options>
          <Script-Binding/>
        </options>
      </control>
      <control>
        <group>[Channel1]</group>
        <key>VDJC.slipB</key>
        <status>0x90</status>
        <midino>0x5A</midino>
        <options>
          <Script-Binding/>
        </options>
      </control>
      <control>
        <group>[Channel1]</group>
        <key>VDJC.tapB</key>
        <status>0x90</status>
        <midino>0x5B</midino>
        <options>
          <Script-Binding/>
        </options>
      </control>
      <control>
        <group>[Channel1]</group>
        <key>VDJC.quantizeB</key>
        <status>0x90</status>
        <midino>0x5C</midino>
        <options>
          <Script-Binding/>
        </options>
      </control>
      <control>
        <group>[Channel1]</group>
        <key>VDJC.keylockB</key>
        <status>0x90</status>
        <midino>0x5D</midino>
        <options>
          <Script-Binding/>
        </options>
      </control>
      <control>
        <group>[Channel1]</group>
        <key>VDJC.syncKeyB</key>
        <status>0x90</status>
        <midino>0x5E</midino>
        <options>
          <Script-Binding/>
        </options>
      </control>
      <control>
        <group>[Channel1]</group>
        <key>VDJC.syncB</key>
        <status>0x90</status>
        <midino>0x5F</midino>
        <options>
          <Script-Binding/>
        </options>
      </control>
      <control>
        <group>[Channel2]</group>
        <key>VDJC.syncKeyB</key>
        <status>0x91</status>
        <midino>0x5E</midino>
        <options>
          <Script-Binding/>
        </options>
      </control>
      <control>
        <group>[Channel2]</group>
        <key>VDJC.syncB</key>
        <status>0x91</status>
        <midino>0x5F</midino>
        <options>
          <Script-Binding/>
        </options>
      </control>
      <control>
        <group>[Channel2]</group>
        <key>VDJC.quantizeB</key>
        <status>0x91</status>
        <midino>0x5C</midino>
        <options>
          <Script-Binding/>
        </options>
      </control>
      <control>
        <group>[Channel2]</group>
        <key>VDJC.keylockB</key>
        <status>0x91</status>
        <midino>0x5D</midino>
        <options>
          <Script-Binding/>
        </options>
      </control>
      <control>
        <group>[Channel2]</group>
        <key>VDJC.slipB</key>
        <status>0x91</status>
        <midino>0x5A</midino>
        <options>
          <Script-Binding/>
        </options>
      </control>
      <control>
        <group>[Channel2]</group>
        <key>VDJC.tapB</key>
        <status>0x91</status>
        <midino>0x5B</midino>
        <options>
          <Script-Binding/>
        </options>
      </control>
      <control>
        <group>[EqualizerRack1_[Channel2]_Effect1]</group>
        <key>VDJC.lowEncoderE</key>
        <status>0xB1</status>
        <midino>0x03</midino>
        <options>
          <Script-Binding/>
        </options>
      </control>
      <control> <!-- QuickEffect Preset Selector -->
        <group>[QuickEffectRack1_[Channel2]]</group>
        <key>VDJC.quickEffectPreset</key>
        <status>0xB1</status>
        <midino>0x04</midino>
        <options>
          <Script-Binding/>
        </options>
      </control>
      <control>
        <group>[EqualizerRack1_[Channel2]_Effect1]</group>
        <key>VDJC.midEncoderE</key>
        <status>0xB1</status>
        <midino>0x02</midino>
        <options>
          <Script-Binding/>
        </options>
      </control>
      <control>
        <group>[EqualizerRack1_[Channel2]_Effect1]</group>
        <key>VDJC.highEncoderE</key>
        <status>0xB1</status>
        <midino>0x01</midino>
        <options>
          <Script-Binding/>
        </options>
      </control>
      <control>
        <group>[Channel2]</group>
        <key>VDJC.pregainEncoderE</key>
        <status>0xB1</status>
        <midino>0x00</midino>
        <options>
          <Script-Binding/>
        </options>
      </control>
      <control>
        <group>[Channel1]</group>
        <key>VDJC.beatloopToggleB</key>
        <status>0x90</status>
        <midino>0x33</midino>
        <options>
          <Script-Binding/>
        </options>
      </control>
      <control>
        <group>[Channel1]</group>
        <key>VDJC.loopInB</key>
        <status>0x90</status>
        <midino>0x34</midino>
        <options>
          <Script-Binding/>
        </options>
      </control>
      <control>
        <group>[Channel1]</group>
        <key>VDJC.loopOutB</key>
        <status>0x90</status>
        <midino>0x35</midino>
        <options>
          <Script-Binding/>
        </options>
      </control>
      <control>
        <group>[Channel1]</group>
        <key>VDJC.loopAnchorB</key>
        <status>0x90</status>
        <midino>0x36</midino>
        <options>
          <Script-Binding/>
        </options>
      </control>
      <control>
        <group>[Channel1]</group>
        <key>VDJC.reloopToggleB</key>
        <status>0x90</status>
        <midino>0x37</midino>
        <options>
          <Script-Binding/>
        </options>
      </control>
      <control>
        <group>[Channel1]</group>
        <key>VDJC.loopDoubleB</key>
        <status>0x90</status>
        <midino>0x38</midino>
        <options>
          <Script-Binding/>
        </options>
      </control>
      <control>
        <group>[Channel1]</group>
        <key>VDJC.loopHalveB</key>
        <status>0x90</status>
        <midino>0x39</midino>
        <options>
          <Script-Binding/>
        </options>
      </control>
      <control>
        <group>[Channel1]</group>
        <key>VDJC.beatjumpBackwardB</key>
        <status>0x90</status>
        <midino>0x3B</midino>
        <options>
          <Script-Binding/>
        </options>
      </control>
      <control>
        <group>[Channel1]</group>
        <key>VDJC.beatjumpForwardB</key>
        <status>0x90</status>
        <midino>0x3A</midino>
        <options>
          <Script-Binding/>
        </options>
      </control>
      <control>
        <group>[Channel1]</group>
        <key>VDJC.beatjumpSizeDoubleB</key>
        <status>0x90</status>
        <midino>0x3C</midino>
        <options>
          <Script-Binding/>
        </options>
      </control>
      <control>
        <group>[Channel1]</group>
        <key>VDJC.beatjumpSizeHalveB</key>
        <status>0x90</status>
        <midino>0x3D</midino>
        <options>
          <Script-Binding/>
        </options>
      </control>
      <control>
        <group>[Channel1]</group>
        <key>VDJC.introStartB</key>
        <status>0x90</status>
        <midino>0x3E</midino>
        <options>
          <Script-Binding/>
        </options>
      </control>
      <control>
        <group>[Channel1]</group>
        <key>VDJC.introEndB</key>
        <status>0x90</status>
        <midino>0x3F</midino>
        <options>
          <Script-Binding/>
        </options>
      </control>
      <control>
        <group>[Channel1]</group>
        <key>VDJC.outroStartB</key>
        <status>0x90</status>
        <midino>0x40</midino>
        <options>
          <Script-Binding/>
        </options>
      </control>
      <control>
        <group>[Channel1]</group>
        <key>VDJC.outroEndB</key>
        <status>0x90</status>
        <midino>0x41</midino>
        <options>
          <Script-Binding/>
        </options>
      </control>
      <control>
        <group>[Channel1]</group>
        <key>VDJC.orientationB</key>
        <status>0x90</status>
        <midino>0x42</midino>
        <options>
          <Script-Binding/>
        </options>
      </control>
      <control>
        <group>[Channel2]</group>
        <key>VDJC.beatloopToggleB</key>
        <status>0x91</status>
        <midino>0x33</midino>
        <options>
          <Script-Binding/>
        </options>
      </control>
      <control>
        <group>[Channel2]</group>
        <key>VDJC.loopInB</key>
        <status>0x91</status>
        <midino>0x34</midino>
        <options>
          <Script-Binding/>
        </options>
      </control>
      <control>
        <group>[Channel2]</group>
        <key>VDJC.loopOutB</key>
        <status>0x91</status>
        <midino>0x35</midino>
        <options>
          <Script-Binding/>
        </options>
      </control>
      <control>
        <group>[Channel2]</group>
        <key>VDJC.loopAnchorB</key>
        <status>0x91</status>
        <midino>0x36</midino>
        <options>
          <Script-Binding/>
        </options>
      </control>
      <control>
        <group>[Channel2]</group>
        <key>VDJC.reloopToggleB</key>
        <status>0x91</status>
        <midino>0x37</midino>
        <options>
          <Script-Binding/>
        </options>
      </control>
      <control>
        <group>[Channel2]</group>
        <key>VDJC.loopDoubleB</key>
        <status>0x91</status>
        <midino>0x38</midino>
        <options>
          <Script-Binding/>
        </options>
      </control>
      <control>
        <group>[Channel2]</group>
        <key>VDJC.loopHalveB</key>
        <status>0x91</status>
        <midino>0x39</midino>
        <options>
          <Script-Binding/>
        </options>
      </control>
      <control>
        <group>[Channel2]</group>
        <key>VDJC.beatjumpBackwardB</key>
        <status>0x91</status>
        <midino>0x3B </midino>
        <options>
          <Script-Binding/>
        </options>
      </control>
      <control>
        <group>[Channel2]</group>
        <key>VDJC.beatjumpForwardB</key>
        <status>0x91</status>
        <midino>0x3A</midino>
        <options>
          <Script-Binding/>
        </options>
      </control>
      <control>
        <group>[Channel2]</group>
        <key>VDJC.beatjumpSizeDoubleB</key>
        <status>0x91</status>
        <midino>0x3C</midino>
        <options>
          <Script-Binding/>
        </options>
      </control>
      <control>
        <group>[Channel2]</group>
        <key>VDJC.beatjumpSizeHalveB</key>
        <status>0x91</status>
        <midino>0x3D</midino>
        <options>
          <Script-Binding/>
        </options>
      </control>
      <control>
        <group>[Channel2]</group>
        <key>VDJC.introStartB</key>
        <status>0x91</status>
        <midino>0x3E</midino>
        <options>
          <Script-Binding/>
        </options>
      </control>
      <control>
        <group>[Channel2]</group>
        <key>VDJC.introEndB</key>
        <status>0x91</status>
        <midino>0x3F</midino>
        <options>
          <Script-Binding/>
        </options>
      </control>
      <control>
        <group>[Channel2]</group>
        <key>VDJC.outroStartB</key>
        <status>0x91</status>
        <midino>0x40</midino>
        <options>
          <Script-Binding/>
        </options>
      </control>
      <control>
        <group>[Channel2]</group>
        <key>VDJC.outroEndB</key>
        <status>0x91</status>
        <midino>0x41</midino>
        <options>
          <Script-Binding/>
        </options>
      </control>
      <control>
        <group>[Channel2]</group>
        <key>VDJC.orientationB</key>
        <status>0x91</status>
        <midino>0x42</midino>
        <options>
          <Script-Binding/>
        </options>
      </control>
      <control>
        <group>[Channel1]</group>
        <key>VDJC.volumeF</key>
        <status>0xB0</status>
        <midino>0x1E</midino>
        <options>
          <Script-Binding/>
        </options>
      </control>
      <control>
        <!--Left Spin--><!-- JogWheel L -->
        <group>[Channel1]</group>
        <key>VDJC.jogW</key>
        <status>0xB0</status>
        <midino>0x1B</midino>
        <description>Wheel Turning (regular)</description>
        <options>
          <Script-Binding/>
        </options>
      </control>
      <control>
      <!-- Left Press Down --><!-- ScrubWheel L -->
        <status>0x90</status>
        <midino>0x0A</midino>
        <group>[Channel1]</group>
        <key>VDJC.jogW</key>
        <description>Jog Wheel L Pressed Down</description>
        <options>
          <Script-Binding/>
        </options>
      </control>
      <control>
        <group>[Channel1]</group>
        <key>VDJC.hotcueB</key>
        <status>0x90</status>
        <midino>0x0B</midino>
        <options>
          <Script-Binding/>
        </options>
      </control>
      <control>
        <group>[Channel1]</group>
        <key>VDJC.hotcueB</key>
        <status>0x90</status>
        <midino>0x0C</midino>
        <options>
          <Script-Binding/>
        </options>
      </control>
      <control>
        <group>[Channel1]</group>
        <key>VDJC.hotcueB</key>
        <status>0x90</status>
        <midino>0x0D</midino>
        <options>
          <Script-Binding/>
        </options>
      </control>
      <control>
        <group>[Channel1]</group>
        <key>VDJC.hotcueB</key>
        <status>0x90</status>
        <midino>0x0E</midino>
        <options>
          <Script-Binding/>
        </options>
      </control>
      <control>
        <group>[Channel1]</group>
        <key>VDJC.hotcueB</key>
        <status>0x90</status>
        <midino>0x0F</midino>
        <options>
          <Script-Binding/>
        </options>
      </control>
      <control>
        <group>[Channel1]</group>
        <key>VDJC.hotcueB</key>
        <status>0x90</status>
        <midino>0x10</midino>
        <options>
          <Script-Binding/>
        </options>
      </control>
      <control>
        <group>[Channel1]</group>
        <key>VDJC.hotcueB</key>
        <status>0x90</status>
        <midino>0x11</midino>
        <options>
          <Script-Binding/>
        </options>
      </control>
      <control>
        <group>[Channel1]</group>
        <key>VDJC.hotcueB</key>
        <status>0x90</status>
        <midino>0x12</midino>
        <options>
          <Script-Binding/>
        </options>
      </control>
      <control>
        <group>[Channel1]</group>
        <key>VDJC.hotcueB</key>
        <status>0x90</status>
        <midino>0x13</midino>
        <options>
          <Script-Binding/>
        </options>
      </control>
      <control>
        <group>[Channel1]</group>
        <key>VDJC.hotcueB</key>
        <status>0x90</status>
        <midino>0x14</midino>
        <options>
          <Script-Binding/>
        </options>
      </control>
      <control>
        <group>[Channel1]</group>
        <key>VDJC.hotcueB</key>
        <status>0x90</status>
        <midino>0x15</midino>
        <options>
          <Script-Binding/>
        </options>
      </control>
      <control>
        <group>[Channel1]</group>
        <key>VDJC.hotcueB</key>
        <status>0x90</status>
        <midino>0x16</midino>
        <options>
          <Script-Binding/>
        </options>
      </control>
      <control>
        <group>[Channel1]</group>
        <key>VDJC.hotcueB</key>
        <status>0x90</status>
        <midino>0x17</midino>
        <options>
          <Script-Binding/>
        </options>
      </control>
      <control>
        <group>[Channel1]</group>
        <key>VDJC.hotcueB</key>
        <status>0x90</status>
        <midino>0x18</midino>
        <options>
          <Script-Binding/>
        </options>
      </control>
      <control>
        <group>[Channel1]</group>
        <key>VDJC.hotcueB</key>
        <status>0x90</status>
        <midino>0x19</midino>
        <options>
          <Script-Binding/>
        </options>
      </control>
      <control>
        <group>[Channel1]</group>
        <key>VDJC.hotcueB</key>
        <status>0x90</status>
        <midino>0x1A</midino>
        <options>
          <Script-Binding/>
        </options>
      </control>
      <control>
        <group>[Channel1]</group>
        <key>VDJC.tempoF</key>
        <status>0xB0</status>
        <midino>0x1D</midino>
        <options>
          <Script-Binding/>
        </options>
      </control>
      <control>
        <group>[Channel2]</group>
        <key>VDJC.tempoF</key>
        <status>0xB1</status>
        <midino>0x1D</midino>
        <options>
          <Script-Binding/>
        </options>
      </control>
      <control>
        <!--Riight Spin--><!-- JogWheel R -->
        <group>[Channel2]</group>
        <key>VDJC.jogW</key>
        <status>0xB1</status>
        <midino>0x1B</midino>
        <description>Wheel Turning (regular)</description>
        <options>
          <Script-Binding/>
        </options>
      </control>
      <control>
        <!-- Right Press Down --><!-- ScrubWheel R -->
        <group>[Channel2]</group>
        <status>0x91</status>
        <midino>0x0A</midino>
        <key>VDJC.jogW</key>
        <description>Jog Wheel R Pressed Down</description>
        <options>
          <Script-Binding/>
        </options>
      </control>
      <control>
        <group>[Channel2]</group>
        <key>VDJC.hotcueB</key>
        <status>0x91</status>
        <midino>0x0B</midino>
        <options>
          <Script-Binding/>
        </options>
      </control>
      <control>
        <group>[Channel2]</group>
        <key>VDJC.hotcueB</key>
        <status>0x91</status>
        <midino>0x0C</midino>
        <options>
          <Script-Binding/>
        </options>
      </control>
      <control>
        <group>[Channel2]</group>
        <key>VDJC.hotcueB</key>
        <status>0x91</status>
        <midino>0x0D</midino>
        <options>
          <Script-Binding/>
        </options>
      </control>
      <control>
        <group>[Channel2]</group>
        <key>VDJC.hotcueB</key>
        <status>0x91</status>
        <midino>0x0E</midino>
        <options>
          <Script-Binding/>
        </options>
      </control>
      <control>
        <group>[Channel2]</group>
        <key>VDJC.hotcueB</key>
        <status>0x91</status>
        <midino>0x0F</midino>
        <options>
          <Script-Binding/>
        </options>
      </control>
      <control>
        <group>[Channel2]</group>
        <key>VDJC.hotcueB</key>
        <status>0x91</status>
        <midino>0x10</midino>
        <options>
          <Script-Binding/>
        </options>
      </control>
      <control>
        <group>[Channel2]</group>
        <key>VDJC.hotcueB</key>
        <status>0x91</status>
        <midino>0x11</midino>
        <options>
          <Script-Binding/>
        </options>
      </control>
      <control>
        <group>[Channel2]</group>
        <key>VDJC.hotcueB</key>
        <status>0x91</status>
        <midino>0x12</midino>
        <options>
          <Script-Binding/>
        </options>
      </control>
      <control>
        <group>[Channel2]</group>
        <key>VDJC.hotcueB</key>
        <status>0x91</status>
        <midino>0x13</midino>
        <options>
          <Script-Binding/>
        </options>
      </control>
      <control>
        <group>[Channel2]</group>
        <key>VDJC.hotcueB</key>
        <status>0x91</status>
        <midino>0x14</midino>
        <options>
          <Script-Binding/>
        </options>
      </control>
      <control>
        <group>[Channel2]</group>
        <key>VDJC.hotcueB</key>
        <status>0x91</status>
        <midino>0x15</midino>
        <options>
          <Script-Binding/>
        </options>
      </control>
      <control>
        <group>[Channel2]</group>
        <key>VDJC.hotcueB</key>
        <status>0x91</status>
        <midino>0x16</midino>
        <options>
          <Script-Binding/>
        </options>
      </control>
      <control>
        <group>[Channel2]</group>
        <key>VDJC.hotcueB</key>
        <status>0x91</status>
        <midino>0x17</midino>
        <options>
          <Script-Binding/>
        </options>
      </control>
      <control>
        <group>[Channel2]</group>
        <key>VDJC.hotcueB</key>
        <status>0x91</status>
        <midino>0x18</midino>
        <options>
          <Script-Binding/>
        </options>
      </control>
      <control>
        <group>[Channel2]</group>
        <key>VDJC.hotcueB</key>
        <status>0x91</status>
        <midino>0x19</midino>
        <options>
          <Script-Binding/>
        </options>
      </control>
      <control>
        <group>[Channel2]</group>
        <key>VDJC.hotcueB</key>
        <status>0x91</status>
        <midino>0x1A</midino>
        <options>
          <Script-Binding/>
        </options>
      </control>
      <control>
        <group>[Channel2]</group>
        <key>VDJC.volumeF</key>
        <status>0xB1</status>
        <midino>0x1E</midino>
        <options>
          <Script-Binding/>
        </options>
      </control>
      <control>
        <group>[Controls]</group>
        <key>VDJC.deckSwitchButton</key>
        <status>0x9F</status>
        <midino>0x01</midino>
        <options>
          <Script-Binding/>
        </options>
      </control>
      <control>
        <group>[Controls]</group>
        <key>VDJC.shiftButton</key>
        <status>0x9F</status>
        <midino>0x03</midino>
        <options>
          <Script-Binding/>
        </options>
      </control>
      <!-- SAMPLER PADS - 16 pulsanti con feedback bidirezionale -->
      <!-- Handler dispatcher: velocity encoding determina quale sampler (1-16) -->
      <control>
        <group>[Master]</group>
        <key>VDJC.samplerPadsHandler</key>
        <status>0x9F</status>
        <midino>0x2B</midino>
        <options>
          <Script-Binding/>
        </options>
      </control>
      <!-- RESYNC REQUEST Handler - VDJC richiede sincronizzazione stato -->
      <control>
        <group>[Master]</group>
        <key>VDJC.resyncAllComponents</key>
        <status>0x9F</status>
        <midino>0x00</midino>
        <options>
          <Script-Binding/>
        </options>
      </control>
      <control>
        <group>[EffectRack1_EffectUnit1]</group>
        <key>VDJC.masterFxAssignButtons[1].input</key>
        <status>0x9F</status>
        <midino>0x51</midino>
        <options>
          <Script-Binding/>
        </options>
      </control>
      <control>
        <group>[EffectRack1_EffectUnit2]</group>
        <key>VDJC.masterFxAssignButtons[2].input</key>
        <status>0x9F</status>
        <midino>0x52</midino>
        <options>
          <Script-Binding/>
        </options>
      </control>
      <control>
        <group>[EffectRack1_EffectUnit3]</group>
        <key>VDJC.masterFxAssignButtons[3].input</key>
        <status>0x9F</status>
        <midino>0x53</midino>
        <options>
          <Script-Binding/>
        </options>
      </control>
      <control>
        <group>[EffectRack1_EffectUnit4]</group>
        <key>VDJC.masterFxAssignButtons[4].input</key>
        <status>0x9F</status>
        <midino>0x54</midino>
        <options>
          <Script-Binding/>
        </options>
      </control>
      <control>
        <group>[Channel1]</group>
        <key>VDJC.FXAssignB</key>
        <status>0x90</status>
        <midino>0x51</midino>
        <options>
          <Script-Binding/>
        </options>
      </control>
      <control>
        <group>[Channel1]</group>
        <key>VDJC.FXAssignB</key>
        <status>0x90</status>
        <midino>0x52</midino>
        <options>
          <Script-Binding/>
        </options>
      </control>
      <control>
        <group>[Channel1]</group>
        <key>VDJC.FXAssignB</key>
        <status>0x90</status>
        <midino>0x53</midino>
        <options>
          <Script-Binding/>
        </options>
      </control>
      <control>
        <group>[Channel1]</group>
        <key>VDJC.FXAssignB</key>
        <status>0x90</status>
        <midino>0x54</midino>
        <options>
          <Script-Binding/>
        </options>
      </control>
      <control>
        <group>[QuickEffectRack1_[Channel1]]</group>
        <key>VDJC.super1EncoderE</key>
        <status>0xB0</status>
        <midino>0x1A</midino>
        <options>
          <Script-Binding/>
        </options>
      </control>
      <control>
        <group>[Channel1]</group>
        <key>VDJC.repeatB</key>
        <status>0x90</status>
        <midino>0x04</midino>
        <options>
          <Script-Binding/>
        </options>
      </control>
      <control>
        <group>[Channel1]</group>
        <key>VDJC.playB</key>
        <status>0x90</status>
        <midino>0x01</midino>
        <options>
          <Script-Binding/>
        </options>
      </control>
      <control>
        <group>[Channel1]</group>
        <key>VDJC.pflB</key>
        <status>0x90</status>
        <midino>0x00</midino>
        <options>
          <Script-Binding/>
        </options>
      </control>
      <control>
        <group>[Channel1]</group>
        <key>VDJC.cueB</key>
        <status>0x90</status>
        <midino>0x02</midino>
        <options>
          <Script-Binding/>
        </options>
      </control>
      <control>
        <group>[Channel1]</group>
        <key>VDJC.ejectB</key>
        <status>0x90</status>
        <midino>0x03</midino>
        <options>
          <Script-Binding/>
        </options>
      </control>
      <control>
        <group>[Master]</group>
        <key>VDJC.crossF.input</key>
        <status>0xBF</status>
        <midino>0x00</midino>
        <options>
          <Script-Binding/>
        </options>
      </control>
      <control>
        <group>[Master]</group>
        <key>VDJC.masterVolume.input</key>
        <status>0xBF</status>
        <midino>0x01</midino>
        <options>
          <Script-Binding/>
        </options>
      </control>
      <control>
        <group>[Master]</group>
        <key>VDJC.masterBalance.input</key>
        <status>0xBF</status>
        <midino>0x02</midino>
        <options>
          <Script-Binding/>
        </options>
      </control>
      <control>
        <group>[Master]</group>
        <key>VDJC.cueVolume.input</key>
        <status>0xBF</status>
        <midino>0x03</midino>
        <options>
          <Script-Binding/>
        </options>
      </control>
      <control>
        <group>[Master]</group>
        <key>VDJC.cueMix.input</key>
        <status>0xBF</status>
        <midino>0x04</midino>
        <options>
          <Script-Binding/>
        </options>
      </control>
      <control>
        <group>[Channel2]</group>
        <key>VDJC.playB</key>
        <status>0x91</status>
        <midino>0x01</midino>
        <options>
          <Script-Binding/>
        </options>
      </control>
      <control>
        <group>[Channel2]</group>
        <key>VDJC.repeatB</key>
        <status>0x91</status>
        <midino>0x04</midino>
        <options>
          <Script-Binding/>
        </options>
      </control>
      <control>
        <group>[Channel2]</group>
        <key>VDJC.cueB</key>
        <status>0x91</status>
        <midino>0x02</midino>
        <options>
          <Script-Binding/>
        </options>
      </control>
      <control>
        <group>[Channel2]</group>
        <key>VDJC.ejectB</key>
        <status>0x91</status>
        <midino>0x03</midino>
        <options>
          <Script-Binding/>
        </options>
      </control>
      <control>
        <group>[Channel2]</group>
        <key>VDJC.pflB</key>
        <status>0x91</status>
        <midino>0x00</midino>
        <options>
          <Script-Binding/>
        </options>
      </control>
      <control>
        <group>[QuickEffectRack1_[Channel2]]</group>
        <key>VDJC.super1EncoderE</key>
        <status>0xB1</status>
        <midino>0x1A</midino>
        <options>
          <Script-Binding/>
        </options>
      </control>
      <control>
        <group>[Channel2]</group>
        <key>VDJC.FXAssignB</key>
        <status>0x91</status>
        <midino>0x51</midino>
        <options>
          <Script-Binding/>
        </options>
      </control>
      <control>
        <group>[Channel2]</group>
        <key>VDJC.FXAssignB</key>
        <status>0x91</status>
        <midino>0x52</midino>
        <options>
          <Script-Binding/>
        </options>
      </control>
      <control>
        <group>[Channel2]</group>
        <key>VDJC.FXAssignB</key>
        <status>0x91</status>
        <midino>0x53</midino>
        <options>
          <Script-Binding/>
        </options>
      </control>
      <control>
        <group>[Channel2]</group>
        <key>VDJC.FXAssignB</key>
        <status>0x91</status>
        <midino>0x54</midino>
        <options>
          <Script-Binding/>
        </options>
      </control>
      <control>
        <group>[Controls]</group>
        <key>VDJC.deckSwitchButton</key>
        <status>0x9F</status>
        <midino>0x02</midino>
        <options>
          <Script-Binding/>
        </options>
      </control>
      <control>
        <group>[Channel1]</group>
        <key>VDJC.BeatGridB</key>
        <status>0x90</status>
        <midino>0x60</midino>
        <options>
          <Script-Binding/>
        </options>
      </control>
      <control>
        <group>[Channel2]</group>
        <key>VDJC.BeatGridB</key>
        <status>0x91</status>
        <midino>0x60</midino>
        <options>
          <Script-Binding/>
        </options>
      </control>
      <!-- Effect Unit-->
      <!-- XY Pad Controls - EffectUnit 1 -->
      <control>
        <group>[EffectRack1_EffectUnit1]</group>
        <key>mix</key>
        <status>0xBF</status>
        <midino>0x50</midino>
        <options>
          <normal/>
        </options>
      </control>
      <control>
        <group>[EffectRack1_EffectUnit1]</group>
        <key>super1</key>
        <status>0xBF</status>
        <midino>0x51</midino>
        <options>
          <normal/>
        </options>
      </control>
      <!-- XY Pad Controls - EffectUnit 2 -->
      <control>
        <group>[EffectRack1_EffectUnit2]</group>
        <key>mix</key>
        <status>0xBF</status>
        <midino>0x52</midino>
        <options>
          <normal/>
        </options>
      </control>
      <control>
        <group>[EffectRack1_EffectUnit2]</group>
        <key>super1</key>
        <status>0xBF</status>
        <midino>0x53</midino>
        <options>
          <normal/>
        </options>
      </control>
      <!-- XY Pad Controls - EffectUnit 3 -->
      <control>
        <group>[EffectRack1_EffectUnit3]</group>
        <key>mix</key>
        <status>0xBF</status>
        <midino>0x54</midino>
        <options>
          <normal/>
        </options>
      </control>
      <control>
        <group>[EffectRack1_EffectUnit3]</group>
        <key>super1</key>
        <status>0xBF</status>
        <midino>0x55</midino>
        <options>
          <normal/>
        </options>
      </control>
      <!-- XY Pad Controls - EffectUnit 4 -->
      <control>
        <group>[EffectRack1_EffectUnit4]</group>
        <key>mix</key>
        <status>0xBF</status>
        <midino>0x56</midino>
        <options>
          <normal/>
        </options>
      </control>
      <control>
        <group>[EffectRack1_EffectUnit4]</group>
        <key>super1</key>
        <status>0xBF</status>
        <midino>0x57</midino>
        <options>
          <normal/>
        </options>
      </control>
      <control>
        <group>[Navigation]</group>
        <key>VDJC.samplerNavigationEnter</key>
        <status>0x99</status>
        <midino>0x00</midino>
        <options>
          <Script-Binding/>
        </options>
      </control>
      <control>
        <group>[Navigation]</group>
        <key>VDJC.samplerNavigation</key>
        <status>0x99</status>
        <midino>0x01</midino>
        <options>
          <Script-Binding/>
        </options>
      </control>
      <control>
        <group>[Navigation]</group>
        <key>VDJC.samplerNavigation</key>
        <status>0x99</status>
        <midino>0x02</midino>
        <options>
          <Script-Binding/>
        </options>
      </control>
      <control>
        <group>[Navigation]</group>
        <key>VDJC.samplerNavigation</key>
        <status>0x99</status>
        <midino>0x03</midino>
        <options>
          <Script-Binding/>
        </options>
      </control>
      <control>
        <group>[Navigation]</group>
        <key>VDJC.samplerNavigation</key>
        <status>0x99</status>
        <midino>0x04</midino>
        <options>
          <Script-Binding/>
        </options>
      </control>
      <control>
        <group>[EffectRack1_EffectUnitN_Effect1]</group>
        <key>VDJC.effect1B</key>
        <status>0x99</status>
        <midino>0x06</midino>
        <options>
          <Script-Binding/>
        </options>
      </control>
      <control>
        <group>[EffectRack1_EffectUnitN_Effect1]</group>
        <key>VDJC.effect1E</key>
        <status>0xB9</status>
        <midino>0x08</midino>
        <options>
          <Script-Binding/>
        </options>
      </control>
      <control>
        <group>[EffectRack1_EffectUnitN_Effect1]</group>
        <key>VDJC.effect1SelectorE</key>
        <status>0xB9</status>
        <midino>0x09</midino>
        <options>
          <Script-Binding/>
        </options>
      </control>
      <control>
        <group>[EffectRack1_EffectUnitN_Effect2]</group>
        <key>VDJC.effect2B</key>
        <status>0x99</status>
        <midino>0x08</midino>
        <options>
          <Script-Binding/>
        </options>
      </control>
      <control>
        <group>[EffectRack1_EffectUnitN_Effect2]</group>
        <key>VDJC.effect2E</key>
        <status>0xB9</status>
        <midino>0x0A</midino>
        <options>
          <Script-Binding/>
        </options>
      </control>
      <control>
        <group>[EffectRack1_EffectUnitN_Effect2]</group>
        <key>VDJC.effect2SelectorE</key>
        <status>0xB9</status>
        <midino>0x0B</midino>
        <options>
          <Script-Binding/>
        </options>
      </control>
      <control>
        <group>[EffectRack1_EffectUnitN_Effect3]</group>
        <key>VDJC.effect3B</key>
        <status>0x99</status>
        <midino>0x0A</midino>
        <options>
          <Script-Binding/>
        </options>
      </control>
      <control>
        <group>[EffectRack1_EffectUnitN_Effect3]</group>
        <key>VDJC.effect3E</key>
        <status>0xB9</status>
        <midino>0x0C</midino>
        <options>
          <Script-Binding/>
        </options>
      </control>
      <control>
        <group>[EffectRack1_EffectUnitN_Effect3]</group>
        <key>VDJC.effect3SelectorE</key>
        <status>0xB9</status>
        <midino>0x0D</midino>
        <options>
          <Script-Binding/>
        </options>
      </control>
      <control>
        <group>[EffectRack1_EffectUnitN]</group>
        <key>VDJC.mixModeB</key>
        <status>0x99</status>
        <midino>0x0B</midino>
        <options>
          <Script-Binding/>
        </options>
      </control>
      <control>
        <group>[EffectRack1_EffectUnitN]</group>
        <key>VDJC.mixE</key>
        <status>0xB9</status>
        <midino>0x0E</midino>
        <options>
          <Script-Binding/>
        </options>
      </control>
      <control>
        <group>[EffectRack1_EffectUnitN]</group>
        <key>VDJC.chainPresetSelectorE</key>
        <status>0xB9</status>
        <midino>0x10</midino>
        <options>
          <Script-Binding/>
        </options>
      </control>
      <control>
        <group>[EffectRack1_EffectUnitN]</group>
        <key>VDJC.super1EffectE</key>
        <status>0xB9</status>
        <midino>0x11</midino>
        <options>
          <Script-Binding/>
        </options>
      </control>
      <control><!--EffectUnit toggle-->
        <group>[Navigation]</group>
        <key>VDJC.effectUnitToggleB</key>
        <status>0x99</status>
        <midino>0x0E</midino>
        <options>
          <Script-Binding/>
        </options>
      </control>
      <control>
        <group>group_[Channel1]_enable</group>
        <key>VDJC.unitAssignChannel1B</key>
        <status>0x99</status>
        <midino>0x0F</midino>
        <options>
          <Script-Binding/>
        </options>
      </control>
      <control>
        <group>group_[Channel2]_enable</group>
        <key>VDJC.unitAssignChannel2B</key>
        <status>0x99</status>
        <midino>0x10</midino>
        <options>
          <Script-Binding/>
        </options>
      </control>
      <control>
        <group>group_[Channel3]_enable</group>
        <key>VDJC.unitAssignChannel3B</key>
        <status>0x99</status>
        <midino>0x11</midino>
        <options>
          <Script-Binding/>
        </options>
      </control>
      <control>
        <group>group_[Channel4]_enable</group>
        <key>VDJC.unitAssignChannel4B</key>
        <status>0x99</status>
        <midino>0x12</midino>
        <options>
          <Script-Binding/>
        </options>
      </control>
      <control>
        <group>group_[Master]_enable</group>
        <key>VDJC.unitAssignMasterB</key>
        <status>0x99</status>
        <midino>0x14</midino>
        <options>
          <Script-Binding/>
        </options>
      </control>
      <control>
        <group>[EffectRack1_EffectUnitN]</group>
        <key>VDJC.unitAssignHeadphoneB</key>
        <status>0x99</status>
        <midino>0x15</midino>
        <options>
          <Script-Binding/>
        </options>
      </control>
      <control>
        <group>[EffectRack1_EffectUnitN_Effect1]</group>
        <key>parameter1</key>
        <status>0xB9</status>
        <midino>0x12</midino>
        <options>
          <Script-Binding/>
        </options>
      </control>
      <control>
        <group>[EffectRack1_EffectUnitN_Effect1]</group>
        <key>VDJC.effectUnit.effect1Invert1.input</key><!--iP1E1 - Label invert Parameter 1 Effect 1-->
        <status>0x99</status>
        <midino>0x18</midino>
        <options>
          <Script-Binding/>
        </options>
      </control>
      <control>
        <group>[EffectRack1_EffectUnitN_Effect1]</group>
        <key>VDJC.effectUnit.effect1Link1.input</key><!--mP1E1 - Label link type middle Parameter 1 Effect 1-->
        <status>0x99</status>
        <midino>0x1A</midino>
        <options>
          <Script-Binding/>
        </options>
      </control>
      <control>
        <group>[EffectRack1_EffectUnitN_Effect1]</group>
        <key>parameter2</key>
        <status>0xB9</status>
        <midino>0x13</midino>
        <options>
          <Script-Binding/>
        </options>
      </control>
      <control>
        <group>[EffectRack1_EffectUnitN_Effect1]</group>
        <key>VDJC.effectUnit.effect1Invert2.input</key><!--iP2E1 - Label invert Parameter 2 Effect 1-->
        <status>0x99</status>
        <midino>0x1D</midino>
        <options>
          <Script-Binding/>
        </options>
      </control>
      <control>
        <group>[EffectRack1_EffectUnitN_Effect1]</group>
        <key>VDJC.effectUnit.effect1Link2.input</key><!--mP2E1 - Label link type middle Parameter 2 Effect 1-->
        <status>0x99</status>
        <midino>0x1F</midino>
        <options>
          <Script-Binding/>
        </options>
      </control>
      <control>
        <group>[EffectRack1_EffectUnitN_Effect1]</group>
        <key>parameter3</key>
        <status>0xB9</status>
        <midino>0x14</midino>
        <options>
          <Script-Binding/>
        </options>
      </control>
      <control>
        <group>[EffectRack1_EffectUnitN_Effect1]</group>
        <key>VDJC.effectUnit.effect1Invert3.input</key><!--iP3E1 - Label invert Parameter 3 Effect 1-->
        <status>0x99</status>
        <midino>0x22</midino>
        <options>
          <Script-Binding/>
        </options>
      </control>
      <control>
        <group>[EffectRack1_EffectUnitN_Effect1]</group>
        <key>VDJC.effectUnit.effect1Link3.input</key><!--mP3E1 - Label link type middle Parameter 3 Effect 1-->
        <status>0x99</status>
        <midino>0x24</midino>
        <options>
          <Script-Binding/>
        </options>
      </control>
      <control>
        <group>[EffectRack1_EffectUnitN_Effect1]</group>
        <key>parameter4</key>
        <status>0xB9</status>
        <midino>0x15</midino>
        <options>
          <Script-Binding/>
        </options>
      </control>
      <control>
        <group>[EffectRack1_EffectUnitN_Effect1]</group>
        <key>VDJC.effectUnit.effect1Invert4.input</key><!--iP4E1 - Label invert Parameter 4 Effect 1-->
        <status>0x99</status>
        <midino>0x27</midino>
        <options>
          <Script-Binding/>
        </options>
      </control>
      <control>
        <group>[EffectRack1_EffectUnitN_Effect1]</group>
        <key>VDJC.effectUnit.effect1Link4.input</key><!--mP4E1 - Label link type middle Parameter 4 Effect 1-->
        <status>0x99</status>
        <midino>0x29</midino>
        <options>
          <Script-Binding/>
        </options>
      </control>
      <control>
        <group>[EffectRack1_EffectUnitN_Effect1]</group>
        <key>parameter5</key>
        <status>0xB9</status>
        <midino>0x16</midino>
        <options>
          <Script-Binding/>
        </options>
      </control>
      <control>
        <group>[EffectRack1_EffectUnitN_Effect1]</group>
        <key>VDJC.effectUnit.effect1Invert5.input</key><!--iP5E1 - Label invert Parameter 5 Effect 1-->
        <status>0x99</status>
        <midino>0x2C</midino>
        <options>
          <Script-Binding/>
        </options>
      </control>
      <control>
        <group>[EffectRack1_EffectUnitN_Effect1]</group>
        <key>VDJC.effectUnit.effect1Link5.input</key><!--mP5E1 - Label link type middle Parameter 5 Effect 1-->
        <status>0x99</status>
        <midino>0x2E</midino>
        <options>
          <Script-Binding/>
        </options>
      </control>
      <control>
        <group>[EffectRack1_EffectUnitN_Effect1]</group>
        <key>parameter6</key>
        <status>0xB9</status>
        <midino>0x17</midino>
        <options>
          <Script-Binding/>
        </options>
      </control>
      <control>
        <group>[EffectRack1_EffectUnitN_Effect1]</group>
        <key>VDJC.effectUnit.effect1Invert6.input</key><!--iP6E1 - Label invert Parameter 6 Effect 1-->
        <status>0x99</status>
        <midino>0x31</midino>
        <options>
          <Script-Binding/>
        </options>
      </control>
      <control>
        <group>[EffectRack1_EffectUnitN_Effect1]</group>
        <key>VDJC.effectUnit.effect1Link6.input</key><!--mP6E1 - Label link type middle Parameter 6 Effect 1-->
        <status>0x99</status>
        <midino>0x33</midino>
        <options>
          <Script-Binding/>
        </options>
      </control>
      <control>
        <group>[EffectRack1_EffectUnitN_Effect1]</group>
        <key>parameter7</key>
        <status>0xB9</status>
        <midino>0x18</midino>
        <options>
          <Script-Binding/>
        </options>
      </control>
      <control>
        <group>[EffectRack1_EffectUnitN_Effect1]</group>
        <key>VDJC.effectUnit.effect1Invert7.input</key><!--iP7E1 - Label invert Parameter 7 Effect 1-->
        <status>0x99</status>
        <midino>0x36</midino>
        <options>
          <Script-Binding/>
        </options>
      </control>
      <control>
        <group>[EffectRack1_EffectUnitN_Effect1]</group>
        <key>VDJC.effectUnit.effect1Link7.input</key><!--mP7E1 - Label link type middle Parameter 7 Effect 1-->
        <status>0x99</status>
        <midino>0x38</midino>
        <options>
          <Script-Binding/>
        </options>
      </control>
      <control>
        <group>[EffectRack1_EffectUnitN_Effect1]</group>
        <key>VDJC.effectUnit.effect1Parameter8.input</key>
        <status>0xB9</status>
        <midino>0x27</midino>
        <options>
          <Script-Binding/>
        </options>
      </control>
      <control>
        <group>[EffectRack1_EffectUnitN_Effect1]</group>
        <key>VDJC.effectUnit.effect1Invert8.input</key><!--iP8E1 - Label invert Parameter 8 Effect 1-->
        <status>0x99</status>
        <midino>0x3D</midino>
        <options>
          <Script-Binding/>
        </options>
      </control>
      <control>
        <group>[EffectRack1_EffectUnitN_Effect1]</group>
        <key>VDJC.effectUnit.effect1Link8.input</key><!--mP8E1 - Label link type middle Parameter 8 Effect 1-->
        <status>0x99</status>
        <midino>0x39</midino>
        <options>
          <Script-Binding/>
        </options>
      </control>
      <control>
        <group>[EffectRack1_EffectUnitN_Effect1]</group>
        <key>VDJC.effect1ButtonParameter1</key>
        <status>0x99</status>
        <midino>0x3A</midino>
        <options>
          <Script-Binding/>
        </options>
      </control>
      <control>
        <group>[EffectRack1_EffectUnitN_Effect1]</group>
        <key>VDJC.effect1ButtonParameter2</key>
        <status>0x99</status>
        <midino>0x3B</midino>
        <options>
          <Script-Binding/>
        </options>
      </control>
      <control>
        <group>[EffectRack1_EffectUnitN_Effect1]</group>
        <key>VDJC.effect1ButtonParameter3</key>
        <status>0x99</status>
        <midino>0x3C</midino>
        <options>
          <Script-Binding/>
        </options>
      </control>
      <control>
        <group>[EffectRack1_EffectUnitN_Effect2]</group>
        <key>parameter1</key>
        <status>0xB9</status>
        <midino>0x19</midino>
        <options>
          <Script-Binding/>
        </options>
      </control>
      <control>
        <group>[EffectRack1_EffectUnitN_Effect2]</group>
        <key>VDJC.effectUnit.effect2Invert1.input</key><!--iP1E2 - Label invert Parameter 1 Effect 2-->
        <status>0x99</status>
        <midino>0x3E</midino>
        <options>
          <Script-Binding/>
        </options>
      </control>
      <control>
        <group>[EffectRack1_EffectUnitN_Effect2]</group>
        <key>VDJC.effectUnit.effect2Link1.input</key><!--mP1E2 - Label link type middle Parameter 1 Effect 2-->
        <status>0x99</status>
        <midino>0x40</midino>
        <options>
          <Script-Binding/>
        </options>
      </control>
      <control>
        <group>[EffectRack1_EffectUnitN_Effect2]</group>
        <key>parameter2</key>
        <status>0xB9</status>
        <midino>0x1A</midino>
        <options>
          <Script-Binding/>
        </options>
      </control>
      <control>
        <group>[EffectRack1_EffectUnitN_Effect2]</group>
        <key>VDJC.effectUnit.effect2Invert2.input</key><!--iP2E2 - Label invert Parameter 2 Effect 2-->
        <status>0x99</status>
        <midino>0x43</midino>
        <options>
          <Script-Binding/>
        </options>
      </control>
      <control>
        <group>[EffectRack1_EffectUnitN_Effect2]</group>
        <key>VDJC.effectUnit.effect2Link2.input</key><!--mP2E2 - Label link type middle Parameter 2 Effect 2-->
        <status>0x99</status>
        <midino>0x45</midino>
        <options>
          <Script-Binding/>
        </options>
      </control>
      <control>
        <group>[EffectRack1_EffectUnitN_Effect2]</group>
        <key>parameter3</key>
        <status>0xB9</status>
        <midino>0x1B</midino>
        <options>
          <Script-Binding/>
        </options>
      </control>
      <control>
        <group>[EffectRack1_EffectUnitN_Effect2]</group>
        <key>VDJC.effectUnit.effect2Invert3.input</key><!--iP3E2 - Label invert Parameter 3 Effect 2-->
        <status>0x99</status>
        <midino>0x48</midino>
        <options>
          <Script-Binding/>
        </options>
      </control>
      <control>
        <group>[EffectRack1_EffectUnitN_Effect2]</group>
        <key>VDJC.effectUnit.effect2Link3.input</key><!--mP3E2 - Label link type middle Parameter 3 Effect 2-->
        <status>0x99</status>
        <midino>0x4A</midino>
        <options>
          <Script-Binding/>
        </options>
      </control>
      <control>
        <group>[EffectRack1_EffectUnitN_Effect2]</group>
        <key>parameter4</key>
        <status>0xB9</status>
        <midino>0x1C</midino>
        <options>
          <Script-Binding/>
        </options>
      </control>
      <control>
        <group>[EffectRack1_EffectUnitN_Effect2]</group>
        <key>VDJC.effectUnit.effect2Invert4.input</key><!--iP4E2 - Label invert Parameter 4 Effect 2-->
        <status>0x99</status>
        <midino>0x4D</midino>
        <options>
          <Script-Binding/>
        </options>
      </control>
      <control>
        <group>[EffectRack1_EffectUnitN_Effect2]</group>
        <key>VDJC.effectUnit.effect2Link4.input</key><!--mP4E2 - Label link type middle Parameter 4 Effect 2-->
        <status>0x99</status>
        <midino>0x4F</midino>
        <options>
          <Script-Binding/>
        </options>
      </control>
      <control>
        <group>[EffectRack1_EffectUnitN_Effect2]</group>
        <key>parameter5</key>
        <status>0xB9</status>
        <midino>0x1D</midino>
        <options>
          <Script-Binding/>
        </options>
      </control>
      <control>
        <group>[EffectRack1_EffectUnitN_Effect2]</group>
        <key>VDJC.effectUnit.effect2Invert5.input</key><!--iP5E2 - Label invert Parameter 5 Effect 2-->
        <status>0x99</status>
        <midino>0x52</midino>
        <options>
          <Script-Binding/>
        </options>
      </control>
      <control>
        <group>[EffectRack1_EffectUnitN_Effect2]</group>
        <key>VDJC.effectUnit.effect2Link5.input</key><!--mP5E2 - Label link type middle Parameter 5 Effect 2-->
        <status>0x99</status>
        <midino>0x54</midino>
        <options>
          <Script-Binding/>
        </options>
      </control>
      <control>
        <group>[EffectRack1_EffectUnitN_Effect2]</group>
        <key>parameter6</key>
        <status>0xB9</status>
        <midino>0x1E</midino>
        <options>
          <Script-Binding/>
        </options>
      </control>
      <control>
        <group>[EffectRack1_EffectUnitN_Effect2]</group>
        <key>VDJC.effectUnit.effect2Invert6.input</key><!--iP6E2 - Label invert Parameter 6 Effect 2-->
        <status>0x99</status>
        <midino>0x57</midino>
        <options>
          <Script-Binding/>
        </options>
      </control>
      <control>
        <group>[EffectRack1_EffectUnitN_Effect2]</group>
        <key>VDJC.effectUnit.effect2Link6.input</key><!--mP6E2 - Label link type middle Parameter 6 Effect 2-->
        <status>0x99</status>
        <midino>0x59</midino>
        <options>
          <Script-Binding/>
        </options>
      </control>
      <control>
        <group>[EffectRack1_EffectUnitN_Effect2]</group>
        <key>parameter7</key>
        <status>0xB9</status>
        <midino>0x1F</midino>
        <options>
          <Script-Binding/>
        </options>
      </control>
      <control>
        <group>[EffectRack1_EffectUnitN_Effect2]</group>
        <key>VDJC.effectUnit.effect2Invert7.input</key><!--iP7E2 - Label invert Parameter 7 Effect 2-->
        <status>0x99</status>
        <midino>0x5C</midino>
        <options>
          <Script-Binding/>
        </options>
      </control>
      <control>
        <group>[EffectRack1_EffectUnitN_Effect2]</group>
        <key>VDJC.effectUnit.effect2Link7.input</key><!--mP7E2 - Label link type middle Parameter 7 Effect 2-->
        <status>0x99</status>
        <midino>0x5E</midino>
        <options>
          <Script-Binding/>
        </options>
      </control>
      <control>
        <group>[EffectRack1_EffectUnitN_Effect2]</group>
        <key>VDJC.effectUnit.effect2Parameter8.input</key>
        <status>0xB9</status>
        <midino>0x2A</midino>
        <options>
          <Script-Binding/>
        </options>
      </control>
      <control>
        <group>[EffectRack1_EffectUnitN_Effect2]</group>
        <key>VDJC.effectUnit.effect2Invert8.input</key><!--iP8E2 - Label invert Parameter 8 Effect 2-->
        <status>0x99</status>
        <midino>0x63</midino>
        <options>
          <Script-Binding/>
        </options>
      </control>
      <control>
        <group>[EffectRack1_EffectUnitN_Effect2]</group>
        <key>VDJC.effectUnit.effect2Link8.input</key><!--mP8E2 - Label link type middle Parameter 8 Effect 2-->
        <status>0x99</status>
        <midino>0x5F</midino>
        <options>
          <Script-Binding/>
        </options>
      </control>
      <control>
        <group>[EffectRack1_EffectUnitN_Effect2]</group>
        <key>VDJC.effect2ButtonParameter1</key>
        <status>0x99</status>
        <midino>0x60</midino>
        <options>
          <Script-Binding/>
        </options>
      </control>
      <control>
        <group>[EffectRack1_EffectUnitN_Effect2]</group>
        <key>VDJC.effect2ButtonParameter2</key>
        <status>0x99</status>
        <midino>0x61</midino>
        <options>
          <Script-Binding/>
        </options>
      </control>
      <control>
        <group>[EffectRack1_EffectUnitN_Effect2]</group>
        <key>VDJC.effect2ButtonParameter3</key>
        <status>0x99</status>
        <midino>0x62</midino>
        <options>
          <Script-Binding/>
        </options>
      </control>
      <control>
        <group>[EffectRack1_EffectUnitN_Effect3]</group>
        <key>parameter1</key>
        <status>0xB9</status>
        <midino>0x20</midino>
        <options>
          <Script-Binding/>
        </options>
      </control>
      <control>
        <group>[EffectRack1_EffectUnitN_Effect3]</group>
        <key>VDJC.effectUnit.effect3Invert1.input</key><!--iP1E3 - Label invert Parameter 1 Effect 3-->
        <status>0x99</status>
        <midino>0x64</midino>
        <options>
          <Script-Binding/>
        </options>
      </control>
      <control>
        <group>[EffectRack1_EffectUnitN_Effect3]</group>
        <key>VDJC.effectUnit.effect3Link1.input</key><!--mP1E3 - Label link type middle Parameter 1 Effect 3-->
        <status>0x99</status>
        <midino>0x66</midino>
        <options>
          <Script-Binding/>
        </options>
      </control>
      <control>
        <group>[EffectRack1_EffectUnitN_Effect3]</group>
        <key>parameter2</key>
        <status>0xB9</status>
        <midino>0x21</midino>
        <options>
          <Script-Binding/>
        </options>
      </control>
      <control>
        <group>[EffectRack1_EffectUnitN_Effect3]</group>
        <key>VDJC.effectUnit.effect3Invert2.input</key><!--iP2E3 - Label invert Parameter 2 Effect 3-->
        <status>0x99</status>
        <midino>0x69</midino>
        <options>
          <Script-Binding/>
        </options>
      </control>
      <control>
        <group>[EffectRack1_EffectUnitN_Effect3]</group>
        <key>VDJC.effectUnit.effect3Link2.input</key><!--mP2E3 - Label link type middle Parameter 2 Effect 3-->
        <status>0x99</status>
        <midino>0x6B</midino>
        <options>
          <Script-Binding/>
        </options>
      </control>
      <control>
        <group>[EffectRack1_EffectUnitN_Effect3]</group>
        <key>parameter3</key>
        <status>0xB9</status>
        <midino>0x22</midino>
        <options>
          <Script-Binding/>
        </options>
      </control>
      <control>
        <group>[EffectRack1_EffectUnitN_Effect3]</group>
        <key>VDJC.effectUnit.effect3Invert3.input</key><!--iP3E3 - Label invert Parameter 3 Effect 3-->
        <status>0x99</status>
        <midino>0x6E</midino>
        <options>
          <Script-Binding/>
        </options>
      </control>
      <control>
        <group>[EffectRack1_EffectUnitN_Effect3]</group>
        <key>VDJC.effectUnit.effect3Link3.input</key><!--mP3E3 - Label link type middle Parameter 3 Effect 3-->
        <status>0x99</status>
        <midino>0x70</midino>
        <options>
          <Script-Binding/>
        </options>
      </control>
      <control>
        <group>[EffectRack1_EffectUnitN_Effect3]</group>
        <key>parameter4</key>
        <status>0xB9</status>
        <midino>0x23</midino>
        <options>
          <Script-Binding/>
        </options>
      </control>
      <control>
        <group>[EffectRack1_EffectUnitN_Effect3]</group>
        <key>VDJC.effectUnit.effect3Invert4.input</key><!--iP4E3 - Label invert Parameter 4 Effect 3-->
        <status>0x99</status>
        <midino>0x73</midino>
        <options>
          <Script-Binding/>
        </options>
      </control>
      <control>
        <group>[EffectRack1_EffectUnitN_Effect3]</group>
        <key>VDJC.effectUnit.effect3Link4.input</key><!--mP4E3 - Label link type middle Parameter 4 Effect 3-->
        <status>0x99</status>
        <midino>0x75</midino>
        <options>
          <Script-Binding/>
        </options>
      </control>
      <control>
        <group>[EffectRack1_EffectUnitN_Effect3]</group>
        <key>parameter5</key>
        <status>0xB9</status>
        <midino>0x24</midino>
        <options>
          <Script-Binding/>
        </options>
      </control>
      <control>
        <group>[EffectRack1_EffectUnitN_Effect3]</group>
        <key>VDJC.effectUnit.effect3Invert5.input</key><!--iP5E3 - Label invert Parameter 5 Effect 3-->
        <status>0x99</status>
        <midino>0x78</midino>
        <options>
          <Script-Binding/>
        </options>
      </control>
      <control>
        <group>[EffectRack1_EffectUnitN_Effect3]</group>
        <key>VDJC.effectUnit.effect3Link5.input</key><!--mP5E3 - Label link type middle Parameter 5 Effect 3-->
        <status>0x99</status>
        <midino>0x7A</midino>
        <options>
          <Script-Binding/>
        </options>
      </control>
      <control>
        <group>[EffectRack1_EffectUnitN_Effect3]</group>
        <key>parameter6</key>
        <status>0xB9</status>
        <midino>0x25</midino>
        <options>
          <Script-Binding/>
        </options>
      </control>
      <control>
        <group>[EffectRack1_EffectUnitN_Effect3]</group>
        <key>VDJC.effectUnit.effect3Invert6.input</key><!--iP6E3 - Label invert Parameter 6 Effect 3-->
        <status>0x99</status>
        <midino>0x7C</midino>
        <options>
          <Script-Binding/>
        </options>
      </control>
      <control>
        <group>[EffectRack1_EffectUnitN_Effect3]</group>
        <key>VDJC.effectUnit.effect3Link6.input</key><!--mP6E3 - Label link type middle Parameter 6 Effect 3-->
        <status>0x99</status>
        <midino>0x7E</midino>
        <options>
          <Script-Binding/>
        </options>
      </control>
      <control>
        <group>[EffectRack1_EffectUnitN_Effect3]</group>
        <key>parameter7</key>
        <status>0xB9</status>
        <midino>0x26</midino>
        <options>
          <Script-Binding/>
        </options>
      </control>
      <control>
        <group>[EffectRack1_EffectUnitN_Effect3]</group>
        <key>VDJC.effectUnit.effect3Invert7.input</key><!--iP7E3 - Label invert Parameter 7 Effect 3-->
        <status>0x99</status>
        <midino>0x17</midino>
        <options>
          <Script-Binding/>
        </options>
      </control>
      <control>
        <group>[EffectRack1_EffectUnitN_Effect3]</group>
        <key>VDJC.effectUnit.effect3Link7.input</key><!--mP7E3 - Label link type middle Parameter 7 Effect 3-->
        <status>0x99</status>
        <midino>0x21</midino>
        <options>
          <Script-Binding/>
        </options>
      </control>
      <control>
        <group>[EffectRack1_EffectUnitN_Effect3]</group>
        <key>VDJC.effectUnit.effect3Parameter8.input</key>
        <status>0xB9</status>
        <midino>0x2B</midino>
        <options>
          <Script-Binding/>
        </options>
      </control>
      <control>
        <group>[EffectRack1_EffectUnitN_Effect3]</group>
        <key>VDJC.effectUnit.effect3Invert8.input</key><!--iP8E3 - Label invert Parameter 8 Effect 3-->
        <status>0x99</status>
        <midino>0x7F</midino>
        <options>
          <Script-Binding/>
        </options>
      </control>
      <control>
        <group>[EffectRack1_EffectUnitN_Effect3]</group>
        <key>VDJC.effectUnit.effect3Link8.input</key><!--mP8E3 - Label link type middle Parameter 8 Effect 3-->
        <status>0x99</status>
        <midino>0x7D</midino>
        <options>
          <Script-Binding/>
        </options>
      </control>
      <control>
        <group>[EffectRack1_EffectUnitN_Effect3]</group>
        <key>VDJC.effect3ButtonParameter1</key>
        <status>0x99</status>
        <midino>0x2B</midino>
        <options>
          <Script-Binding/>
        </options>
      </control>
      <control>
        <group>[EffectRack1_EffectUnitN_Effect3]</group>
        <key>VDJC.effect3ButtonParameter2</key>
        <status>0x99</status>
        <midino>0x30</midino>
        <options>
          <Script-Binding/>
        </options>
      </control>
      <control>
        <group>[EffectRack1_EffectUnitN_Effect3]</group>
        <key>VDJC.effect3ButtonParameter3</key>
        <status>0x99</status>
        <midino>0x35</midino>
        <options>
          <Script-Binding/>
        </options>
      </control>
      <control>
        <group>[Controls]</group>
        <key>VDJC.samplerToggleAssignment</key>
        <status>0x99</status>
        <midino>0x0D</midino>
        <options>
          <Script-Binding/>
        </options>
      </control>
      <!-- Sampler Bank A Target Change (CH 5 CC 0x7F) -->
      <control>
        <group>[Controls]</group>
        <key>VDJC.samplerBankChangeTarget</key>
        <status>0xB4</status>
        <midino>0x7F</midino>
        <options>
          <Script-Binding/>
        </options>
      </control>
      <!-- Sampler Bank B Target Change (CH 6 CC 0x7F) -->
      <control>
        <group>[Controls]</group>
        <key>VDJC.samplerBankChangeTarget</key>
        <status>0xB5</status>
        <midino>0x7F</midino>
        <options>
          <Script-Binding/>
        </options>
      </control>
      <!-- ==================== SAMPLER BANK A FULL CONTROLS - Channel 5 (0x94/0xB4) ==================== -->
      <!-- Encoders CC 0xB4 -->
      <control>
        <group>[Controls]</group>
        <key>VDJC.pregainEncoderE</key>
        <status>0xB4</status>
        <midino>0x00</midino>
        <options>
          <Script-Binding/>
        </options>
      </control>
      <control>
        <group>[Controls]</group>
        <key>VDJC.volumeF</key>
        <status>0xB4</status>
        <midino>0x1E</midino>
        <options>
          <Script-Binding/>
        </options>
      </control>
      <control>
        <group>[Controls]</group>
        <key>VDJC.tempoF</key>
        <status>0xB4</status>
        <midino>0x1D</midino>
        <options>
          <Script-Binding/>
        </options>
      </control>
      <control>
        <group>[Controls]</group>
        <key>VDJC.jogW</key>
        <status>0xB4</status>
        <midino>0x1B</midino>
        <options>
          <Script-Binding/>
        </options>
      </control>
      <control>
        <!-- JogWheel Touch (Scratch Mode) -->
        <group>[Controls]</group>
        <key>VDJC.jogW</key>
        <status>0x94</status>
        <midino>0x0A</midino>
        <options>
          <Script-Binding/>
        </options>
      </control>
      <!-- Buttons Note On 0x94 -->
      <control>
        <group>[Controls]</group>
        <key>VDJC.playB</key>
        <status>0x94</status>
        <midino>0x01</midino>
        <options>
          <Script-Binding/>
        </options>
      </control>
      <control>
        <group>[Controls]</group>
        <key>VDJC.cueB</key>
        <status>0x94</status>
        <midino>0x02</midino>
        <options>
          <Script-Binding/>
        </options>
      </control>
      <control>
        <group>[Controls]</group>
        <key>VDJC.syncB</key>
        <status>0x94</status>
        <midino>0x5F</midino>
        <options>
          <Script-Binding/>
        </options>
      </control>
      <control>
        <group>[Controls]</group>
        <key>VDJC.syncKeyB</key>
        <status>0x94</status>
        <midino>0x5E</midino>
        <options>
          <Script-Binding/>
        </options>
      </control>
      <control>
        <group>[Controls]</group>
        <key>VDJC.repeatB</key>
        <status>0x94</status>
        <midino>0x04</midino>
        <options>
          <Script-Binding/>
        </options>
      </control>
      <control>
        <group>[Controls]</group>
        <key>VDJC.keylockB</key>
        <status>0x94</status>
        <midino>0x5D</midino>
        <options>
          <Script-Binding/>
        </options>
      </control>
      <control>
        <group>[Controls]</group>
        <key>VDJC.quantizeB</key>
        <status>0x94</status>
        <midino>0x5C</midino>
        <options>
          <Script-Binding/>
        </options>
      </control>
      <control>
        <group>[Controls]</group>
        <key>VDJC.slipB</key>
        <status>0x94</status>
        <midino>0x5A</midino>
        <options>
          <Script-Binding/>
        </options>
      </control>
      <control>
        <group>[Controls]</group>
        <key>VDJC.tapB</key>
        <status>0x94</status>
        <midino>0x5B</midino>
        <options>
          <Script-Binding/>
        </options>
      </control>
      <control>
        <group>[Controls]</group>
        <key>VDJC.FXAssignB</key>
        <status>0x94</status>
        <midino>0x10</midino>
        <options>
          <Script-Binding/>
        </options>
      </control>
      <control>
        <group>[Controls]</group>
        <key>VDJC.FXAssignB</key>
        <status>0x94</status>
        <midino>0x11</midino>
        <options>
          <Script-Binding/>
        </options>
      </control>
      <control>
        <group>[Controls]</group>
        <key>VDJC.FXAssignB</key>
        <status>0x94</status>
        <midino>0x12</midino>
        <options>
          <Script-Binding/>
        </options>
      </control>
      <control>
        <group>[Controls]</group>
        <key>VDJC.FXAssignB</key>
        <status>0x94</status>
        <midino>0x13</midino>
        <options>
          <Script-Binding/>
        </options>
      </control>
      <!-- Hotcues 1-16 Note On 0x94 -->
      <control>
        <group>[Controls]</group>
        <key>VDJC.hotcueB</key>
        <status>0x94</status>
        <midino>0x0B</midino>
        <options>
          <Script-Binding/>
        </options>
      </control>
      <control>
        <group>[Controls]</group>
        <key>VDJC.hotcueB</key>
        <status>0x94</status>
        <midino>0x0C</midino>
        <options>
          <Script-Binding/>
        </options>
      </control>
      <control>
        <group>[Controls]</group>
        <key>VDJC.hotcueB</key>
        <status>0x94</status>
        <midino>0x0D</midino>
        <options>
          <Script-Binding/>
        </options>
      </control>
      <control>
        <group>[Controls]</group>
        <key>VDJC.hotcueB</key>
        <status>0x94</status>
        <midino>0x0E</midino>
        <options>
          <Script-Binding/>
        </options>
      </control>
      <control>
        <group>[Controls]</group>
        <key>VDJC.hotcueB</key>
        <status>0x94</status>
        <midino>0x0F</midino>
        <options>
          <Script-Binding/>
        </options>
      </control>
      <control>
        <group>[Controls]</group>
        <key>VDJC.hotcueB</key>
        <status>0x94</status>
        <midino>0x10</midino>
        <options>
          <Script-Binding/>
        </options>
      </control>
      <control>
        <group>[Controls]</group>
        <key>VDJC.hotcueB</key>
        <status>0x94</status>
        <midino>0x11</midino>
        <options>
          <Script-Binding/>
        </options>
      </control>
      <control>
        <group>[Controls]</group>
        <key>VDJC.hotcueB</key>
        <status>0x94</status>
        <midino>0x12</midino>
        <options>
          <Script-Binding/>
        </options>
      </control>
      <control>
        <group>[Controls]</group>
        <key>VDJC.hotcueB</key>
        <status>0x94</status>
        <midino>0x13</midino>
        <options>
          <Script-Binding/>
        </options>
      </control>
      <control>
        <group>[Controls]</group>
        <key>VDJC.hotcueB</key>
        <status>0x94</status>
        <midino>0x14</midino>
        <options>
          <Script-Binding/>
        </options>
      </control>
      <control>
        <group>[Controls]</group>
        <key>VDJC.hotcueB</key>
        <status>0x94</status>
        <midino>0x15</midino>
        <options>
          <Script-Binding/>
        </options>
      </control>
      <control>
        <group>[Controls]</group>
        <key>VDJC.hotcueB</key>
        <status>0x94</status>
        <midino>0x16</midino>
        <options>
          <Script-Binding/>
        </options>
      </control>
      <control>
        <group>[Controls]</group>
        <key>VDJC.hotcueB</key>
        <status>0x94</status>
        <midino>0x17</midino>
        <options>
          <Script-Binding/>
        </options>
      </control>
      <control>
        <group>[Controls]</group>
        <key>VDJC.hotcueB</key>
        <status>0x94</status>
        <midino>0x18</midino>
        <options>
          <Script-Binding/>
        </options>
      </control>
      <control>
        <group>[Controls]</group>
        <key>VDJC.hotcueB</key>
        <status>0x94</status>
        <midino>0x19</midino>
        <options>
          <Script-Binding/>
        </options>
      </control>
      <control>
        <group>[Controls]</group>
        <key>VDJC.hotcueB</key>
        <status>0x94</status>
        <midino>0x1A</midino>
        <options>
          <Script-Binding/>
        </options>
      </control>
      <!-- Loop controls Note On 0x94 -->
      <control>
        <group>[Controls]</group>
        <key>VDJC.beatloopToggleB</key>
        <status>0x94</status>
        <midino>0x33</midino>
        <options>
          <Script-Binding/>
        </options>
      </control>
      <control>
        <group>[Controls]</group>
        <key>VDJC.reloopToggleB</key>
        <status>0x94</status>
        <midino>0x37</midino>
        <options>
          <Script-Binding/>
        </options>
      </control>
      <control>
        <group>[Controls]</group>
        <key>VDJC.loopInB</key>
        <status>0x94</status>
        <midino>0x34</midino>
        <options>
          <Script-Binding/>
        </options>
      </control>
      <control>
        <group>[Controls]</group>
        <key>VDJC.loopOutB</key>
        <status>0x94</status>
        <midino>0x35</midino>
        <options>
          <Script-Binding/>
        </options>
      </control>
      <control>
        <group>[Controls]</group>
        <key>VDJC.loopAnchorB</key>
        <status>0x94</status>
        <midino>0x36</midino>
        <options>
          <Script-Binding/>
        </options>
      </control>
      <control>
        <group>[Controls]</group>
        <key>VDJC.loopDoubleB</key>
        <status>0x94</status>
        <midino>0x38</midino>
        <options>
          <Script-Binding/>
        </options>
      </control>
      <control>
        <group>[Controls]</group>
        <key>VDJC.loopHalveB</key>
        <status>0x94</status>
        <midino>0x39</midino>
        <options>
          <Script-Binding/>
        </options>
      </control>
      <control>
        <group>[Controls]</group>
        <key>VDJC.beatjumpBackwardB</key>
        <status>0x94</status>
        <midino>0x3B</midino>
        <options>
          <Script-Binding/>
        </options>
      </control>
      <control>
        <group>[Controls]</group>
        <key>VDJC.beatjumpForwardB</key>
        <status>0x94</status>
        <midino>0x3A</midino>
        <options>
          <Script-Binding/>
        </options>
      </control>
      <control>
        <group>[Controls]</group>
        <key>VDJC.beatjumpSizeDoubleB</key>
        <status>0x94</status>
        <midino>0x3C</midino>
        <options>
          <Script-Binding/>
        </options>
      </control>
      <control>
        <group>[Controls]</group>
        <key>VDJC.beatjumpSizeHalveB</key>
        <status>0x94</status>
        <midino>0x3D</midino>
        <options>
          <Script-Binding/>
        </options>
      </control>
      <!-- Marker controls Note On 0x94 -->
      <control>
        <group>[Controls]</group>
        <key>VDJC.introStartB</key>
        <status>0x94</status>
        <midino>0x50</midino>
        <options>
          <Script-Binding/>
        </options>
      </control>
      <control>
        <group>[Controls]</group>
        <key>VDJC.introEndB</key>
        <status>0x94</status>
        <midino>0x51</midino>
        <options>
          <Script-Binding/>
        </options>
      </control>
      <control>
        <group>[Controls]</group>
        <key>VDJC.outroStartB</key>
        <status>0x94</status>
        <midino>0x52</midino>
        <options>
          <Script-Binding/>
        </options>
      </control>
      <control>
        <group>[Controls]</group>
        <key>VDJC.outroEndB</key>
        <status>0x94</status>
        <midino>0x53</midino>
        <options>
          <Script-Binding/>
        </options>
      </control>
      <!-- EQ Kill + QuickEffect Note On 0x94 -->
      <control>
        <group>[Controls]</group>
        <key>VDJC.EQHighKillB</key>
        <status>0x94</status>
        <midino>0x54</midino>
        <options>
          <Script-Binding/>
        </options>
      </control>
      <control>
        <group>[Controls]</group>
        <key>VDJC.EQMidKillB</key>
        <status>0x94</status>
        <midino>0x55</midino>
        <options>
          <Script-Binding/>
        </options>
      </control>
      <control>
        <group>[Controls]</group>
        <key>VDJC.EQLowKillB</key>
        <status>0x94</status>
        <midino>0x56</midino>
        <options>
          <Script-Binding/>
        </options>
      </control>
      <control>
        <group>[Controls]</group>
        <key>VDJC.QuickEffB</key>
        <status>0x94</status>
        <midino>0x57</midino>
        <options>
          <Script-Binding/>
        </options>
      </control>
      <!-- Additional controls Note On 0x94 -->
      <control>
        <group>[Controls]</group>
        <key>VDJC.pflB</key>
        <status>0x94</status>
        <midino>0x00</midino>
        <options>
          <Script-Binding/>
        </options>
      </control>
      <control>
        <group>[Controls]</group>
        <key>VDJC.orientationB</key>
        <status>0x94</status>
        <midino>0x42</midino>
        <options>
          <Script-Binding/>
        </options>
      </control>
      <control>
        <group>[Controls]</group>
        <key>VDJC.ejectB</key>
        <status>0x94</status>
        <midino>0x03</midino>
        <options>
          <Script-Binding/>
        </options>
      </control>
      <!-- ==================== SAMPLER BANK B FULL CONTROLS - Channel 6 (0x95/0xB5) ==================== -->
      <!-- Encoders CC 0xB5 -->
      <control>
        <group>[Controls]</group>
        <key>VDJC.pregainEncoderE</key>
        <status>0xB5</status>
        <midino>0x00</midino>
        <options>
          <Script-Binding/>
        </options>
      </control>
      <control>
        <group>[Controls]</group>
        <key>VDJC.volumeF</key>
        <status>0xB5</status>
        <midino>0x1E</midino>
        <options>
          <Script-Binding/>
        </options>
      </control>
      <control>
        <group>[Controls]</group>
        <key>VDJC.tempoF</key>
        <status>0xB5</status>
        <midino>0x1D</midino>
        <options>
          <Script-Binding/>
        </options>
      </control>
      <control>
        <group>[Controls]</group>
        <key>VDJC.jogW</key>
        <status>0xB5</status>
        <midino>0x1B</midino>
        <options>
          <Script-Binding/>
        </options>
      </control>
      <control>
        <!-- JogWheel Touch (Scratch Mode) -->
        <group>[Controls]</group>
        <key>VDJC.jogW</key>
        <status>0x95</status>
        <midino>0x0A</midino>
        <options>
          <Script-Binding/>
        </options>
      </control>
      <!-- Buttons Note On 0x95 -->
      <control>
        <group>[Controls]</group>
        <key>VDJC.playB</key>
        <status>0x95</status>
        <midino>0x01</midino>
        <options>
          <Script-Binding/>
        </options>
      </control>
      <control>
        <group>[Controls]</group>
        <key>VDJC.cueB</key>
        <status>0x95</status>
        <midino>0x02</midino>
        <options>
          <Script-Binding/>
        </options>
      </control>
      <control>
        <group>[Controls]</group>
        <key>VDJC.syncB</key>
        <status>0x95</status>
        <midino>0x5F</midino>
        <options>
          <Script-Binding/>
        </options>
      </control>
      <control>
        <group>[Controls]</group>
        <key>VDJC.syncKeyB</key>
        <status>0x95</status>
        <midino>0x5E</midino>
        <options>
          <Script-Binding/>
        </options>
      </control>
      <control>
        <group>[Controls]</group>
        <key>VDJC.repeatB</key>
        <status>0x95</status>
        <midino>0x04</midino>
        <options>
          <Script-Binding/>
        </options>
      </control>
      <control>
        <group>[Controls]</group>
        <key>VDJC.keylockB</key>
        <status>0x95</status>
        <midino>0x5D</midino>
        <options>
          <Script-Binding/>
        </options>
      </control>
      <control>
        <group>[Controls]</group>
        <key>VDJC.quantizeB</key>
        <status>0x95</status>
        <midino>0x5C</midino>
        <options>
          <Script-Binding/>
        </options>
      </control>
      <control>
        <group>[Controls]</group>
        <key>VDJC.slipB</key>
        <status>0x95</status>
        <midino>0x5A</midino>
        <options>
          <Script-Binding/>
        </options>
      </control>
      <control>
        <group>[Controls]</group>
        <key>VDJC.tapB</key>
        <status>0x95</status>
        <midino>0x5B</midino>
        <options>
          <Script-Binding/>
        </options>
      </control>
      <control>
        <group>[Controls]</group>
        <key>VDJC.FXAssignB</key>
        <status>0x95</status>
        <midino>0x10</midino>
        <options>
          <Script-Binding/>
        </options>
      </control>
      <control>
        <group>[Controls]</group>
        <key>VDJC.FXAssignB</key>
        <status>0x95</status>
        <midino>0x11</midino>
        <options>
          <Script-Binding/>
        </options>
      </control>
      <control>
        <group>[Controls]</group>
        <key>VDJC.FXAssignB</key>
        <status>0x95</status>
        <midino>0x12</midino>
        <options>
          <Script-Binding/>
        </options>
      </control>
      <control>
        <group>[Controls]</group>
        <key>VDJC.FXAssignB</key>
        <status>0x95</status>
        <midino>0x13</midino>
        <options>
          <Script-Binding/>
        </options>
      </control>
      <!-- Hotcues 1-16 Note On 0x95 -->
      <control>
        <group>[Controls]</group>
        <key>VDJC.hotcueB</key>
        <status>0x95</status>
        <midino>0x0B</midino>
        <options>
          <Script-Binding/>
        </options>
      </control>
      <control>
        <group>[Controls]</group>
        <key>VDJC.hotcueB</key>
        <status>0x95</status>
        <midino>0x0C</midino>
        <options>
          <Script-Binding/>
        </options>
      </control>
      <control>
        <group>[Controls]</group>
        <key>VDJC.hotcueB</key>
        <status>0x95</status>
        <midino>0x0D</midino>
        <options>
          <Script-Binding/>
        </options>
      </control>
      <control>
        <group>[Controls]</group>
        <key>VDJC.hotcueB</key>
        <status>0x95</status>
        <midino>0x0E</midino>
        <options>
          <Script-Binding/>
        </options>
      </control>
      <control>
        <group>[Controls]</group>
        <key>VDJC.hotcueB</key>
        <status>0x95</status>
        <midino>0x0F</midino>
        <options>
          <Script-Binding/>
        </options>
      </control>
      <control>
        <group>[Controls]</group>
        <key>VDJC.hotcueB</key>
        <status>0x95</status>
        <midino>0x10</midino>
        <options>
          <Script-Binding/>
        </options>
      </control>
      <control>
        <group>[Controls]</group>
        <key>VDJC.hotcueB</key>
        <status>0x95</status>
        <midino>0x11</midino>
        <options>
          <Script-Binding/>
        </options>
      </control>
      <control>
        <group>[Controls]</group>
        <key>VDJC.hotcueB</key>
        <status>0x95</status>
        <midino>0x12</midino>
        <options>
          <Script-Binding/>
        </options>
      </control>
      <control>
        <group>[Controls]</group>
        <key>VDJC.hotcueB</key>
        <status>0x95</status>
        <midino>0x13</midino>
        <options>
          <Script-Binding/>
        </options>
      </control>
      <control>
        <group>[Controls]</group>
        <key>VDJC.hotcueB</key>
        <status>0x95</status>
        <midino>0x14</midino>
        <options>
          <Script-Binding/>
        </options>
      </control>
      <control>
        <group>[Controls]</group>
        <key>VDJC.hotcueB</key>
        <status>0x95</status>
        <midino>0x15</midino>
        <options>
          <Script-Binding/>
        </options>
      </control>
      <control>
        <group>[Controls]</group>
        <key>VDJC.hotcueB</key>
        <status>0x95</status>
        <midino>0x16</midino>
        <options>
          <Script-Binding/>
        </options>
      </control>
      <control>
        <group>[Controls]</group>
        <key>VDJC.hotcueB</key>
        <status>0x95</status>
        <midino>0x17</midino>
        <options>
          <Script-Binding/>
        </options>
      </control>
      <control>
        <group>[Controls]</group>
        <key>VDJC.hotcueB</key>
        <status>0x95</status>
        <midino>0x18</midino>
        <options>
          <Script-Binding/>
        </options>
      </control>
      <control>
        <group>[Controls]</group>
        <key>VDJC.hotcueB</key>
        <status>0x95</status>
        <midino>0x19</midino>
        <options>
          <Script-Binding/>
        </options>
      </control>
      <control>
        <group>[Controls]</group>
        <key>VDJC.hotcueB</key>
        <status>0x95</status>
        <midino>0x1A</midino>
        <options>
          <Script-Binding/>
        </options>
      </control>
      <!-- Loop controls Note On 0x95 -->
      <control>
        <group>[Controls]</group>
        <key>VDJC.beatloopToggleB</key>
        <status>0x95</status>
        <midino>0x33</midino>
        <options>
          <Script-Binding/>
        </options>
      </control>
      <control>
        <group>[Controls]</group>
        <key>VDJC.reloopToggleB</key>
        <status>0x95</status>
        <midino>0x37</midino>
        <options>
          <Script-Binding/>
        </options>
      </control>
      <control>
        <group>[Controls]</group>
        <key>VDJC.loopInB</key>
        <status>0x95</status>
        <midino>0x34</midino>
        <options>
          <Script-Binding/>
        </options>
      </control>
      <control>
        <group>[Controls]</group>
        <key>VDJC.loopOutB</key>
        <status>0x95</status>
        <midino>0x35</midino>
        <options>
          <Script-Binding/>
        </options>
      </control>
      <control>
        <group>[Controls]</group>
        <key>VDJC.loopAnchorB</key>
        <status>0x95</status>
        <midino>0x36</midino>
        <options>
          <Script-Binding/>
        </options>
      </control>
      <control>
        <group>[Controls]</group>
        <key>VDJC.loopDoubleB</key>
        <status>0x95</status>
        <midino>0x38</midino>
        <options>
          <Script-Binding/>
        </options>
      </control>
      <control>
        <group>[Controls]</group>
        <key>VDJC.loopHalveB</key>
        <status>0x95</status>
        <midino>0x39</midino>
        <options>
          <Script-Binding/>
        </options>
      </control>
      <control>
        <group>[Controls]</group>
        <key>VDJC.beatjumpBackwardB</key>
        <status>0x95</status>
        <midino>0x3B</midino>
        <options>
          <Script-Binding/>
        </options>
      </control>
      <control>
        <group>[Controls]</group>
        <key>VDJC.beatjumpForwardB</key>
        <status>0x95</status>
        <midino>0x3A</midino>
        <options>
          <Script-Binding/>
        </options>
      </control>
      <control>
        <group>[Controls]</group>
        <key>VDJC.beatjumpSizeDoubleB</key>
        <status>0x95</status>
        <midino>0x3C</midino>
        <options>
          <Script-Binding/>
        </options>
      </control>
      <control>
        <group>[Controls]</group>
        <key>VDJC.beatjumpSizeHalveB</key>
        <status>0x95</status>
        <midino>0x3D</midino>
        <options>
          <Script-Binding/>
        </options>
      </control>
      <!-- Marker controls Note On 0x95 -->
      <control>
        <group>[Controls]</group>
        <key>VDJC.introStartB</key>
        <status>0x95</status>
        <midino>0x50</midino>
        <options>
          <Script-Binding/>
        </options>
      </control>
      <control>
        <group>[Controls]</group>
        <key>VDJC.introEndB</key>
        <status>0x95</status>
        <midino>0x51</midino>
        <options>
          <Script-Binding/>
        </options>
      </control>
      <control>
        <group>[Controls]</group>
        <key>VDJC.outroStartB</key>
        <status>0x95</status>
        <midino>0x52</midino>
        <options>
          <Script-Binding/>
        </options>
      </control>
      <control>
        <group>[Controls]</group>
        <key>VDJC.outroEndB</key>
        <status>0x95</status>
        <midino>0x53</midino>
        <options>
          <Script-Binding/>
        </options>
      </control>
      <!-- EQ Kill + QuickEffect Note On 0x95 -->
      <control>
        <group>[Controls]</group>
        <key>VDJC.EQHighKillB</key>
        <status>0x95</status>
        <midino>0x54</midino>
        <options>
          <Script-Binding/>
        </options>
      </control>
      <control>
        <group>[Controls]</group>
        <key>VDJC.EQMidKillB</key>
        <status>0x95</status>
        <midino>0x55</midino>
        <options>
          <Script-Binding/>
        </options>
      </control>
      <control>
        <group>[Controls]</group>
        <key>VDJC.EQLowKillB</key>
        <status>0x95</status>
        <midino>0x56</midino>
        <options>
          <Script-Binding/>
        </options>
      </control>
      <control>
        <group>[Controls]</group>
        <key>VDJC.QuickEffB</key>
        <status>0x95</status>
        <midino>0x57</midino>
        <options>
          <Script-Binding/>
        </options>
      </control>
      <!-- Additional controls Note On 0x95 -->
      <control>
        <group>[Controls]</group>
        <key>VDJC.pflB</key>
        <status>0x95</status>
        <midino>0x00</midino>
        <options>
          <Script-Binding/>
        </options>
      </control>
      <control>
        <group>[Controls]</group>
        <key>VDJC.orientationB</key>
        <status>0x95</status>
        <midino>0x42</midino>
        <options>
          <Script-Binding/>
        </options>
      </control>
      <control>
        <group>[Controls]</group>
        <key>VDJC.ejectB</key>
        <status>0x95</status>
        <midino>0x03</midino>
        <options>
          <Script-Binding/>
        </options>
      </control>
      <control>
        <group>SysEx</group><!-- Mapping per messaggi SysEx VDJC Protocol -->
        <key>VDJC.incomingData</key>
        <status>0xF0</status>
        <options>
          <Script-Binding/>
        </options>
      </control>
      <!-- Library Navigation - D-Pad (CH 16 Note On) -->
      <control>
        <group>[Library]</group>
        <key>VDJC.libraryNavUp</key>
        <status>0x9F</status>
        <midino>0x10</midino>
        <options>
          <Script-Binding/>
        </options>
      </control>
      <control>
        <group>[Library]</group>
        <key>VDJC.libraryNavDown</key>
        <status>0x9F</status>
        <midino>0x11</midino>
        <options>
          <Script-Binding/>
        </options>
      </control>
      <control>
        <group>[Library]</group>
        <key>VDJC.libraryNavLeft</key>
        <status>0x9F</status>
        <midino>0x12</midino>
        <options>
          <Script-Binding/>
        </options>
      </control>
      <control>
        <group>[Library]</group>
        <key>VDJC.libraryNavRight</key>
        <status>0x9F</status>
        <midino>0x13</midino>
        <options>
          <Script-Binding/>
        </options>
      </control>
      <control>
        <group>[Library]</group>
        <key>VDJC.libraryNavCenter</key>
        <status>0x9F</status>
        <midino>0x14</midino>
        <options>
          <Script-Binding/>
        </options>
      </control>
      <!-- Library Load to Channel1 (CH 16) -->
      <control>
        <group>[Library]</group>
        <key>VDJC.libraryLoadToChannel1</key>
        <status>0x9F</status>
        <midino>0x15</midino>
        <options>
          <Script-Binding/>
        </options>
      </control>
      <!-- Library Load to Channel2 (CH 16) -->
      <control>
        <group>[Library]</group>
        <key>VDJC.libraryLoadToChannel2</key>
        <status>0x9F</status>
        <midino>0x16</midino>
        <options>
          <Script-Binding/>
        </options>
      </control>
      <!-- Library Load to Channel3 (CH 16) -->
      <control>
        <group>[Library]</group>
        <key>VDJC.libraryLoadToChannel3</key>
        <status>0x9F</status>
        <midino>0x17</midino>
        <options>
          <Script-Binding/>
        </options>
      </control>
      <!-- Library Load to Channel4 (CH 16) -->
      <control>
        <group>[Library]</group>
        <key>VDJC.libraryLoadToChannel4</key>
        <status>0x9F</status>
        <midino>0x18</midino>
        <options>
          <Script-Binding/>
        </options>
      </control>
      <!-- Library Load to PreviewDeck1 (CH 16) -->
      <control>
        <group>[Library]</group>
        <key>VDJC.libraryLoadToPreviewDeck</key>
        <status>0x9F</status>
        <midino>0x19</midino>
        <options>
          <Script-Binding/>
        </options>
      </control>
      <!-- Library Load to Sampler 1-64 (CH 16) -->
      <control>
        <group>[Library]</group>
        <key>VDJC.libraryLoadToSampler</key>
        <status>0x9F</status>
        <midino>0x1A</midino>
        <options>
          <Script-Binding/>
        </options>
      </control>
      <!-- Library Navigation - ScrollRing (CH 16 CC) -->
      <control>
        <group>[Library]</group>
        <key>VDJC.libraryScroll</key>
        <status>0xBF</status>
        <midino>0x10</midino>
        <options>
          <Script-Binding/>
        </options>
      </control>
      <!-- Library Focus Widget (CH 16 CC) -->
      <control>
        <group>[Library]</group>
        <key>VDJC.libraryFocusWidget</key>
        <status>0xBF</status>
        <midino>0x11</midino>
        <options>
          <Script-Binding/>
        </options>
      </control>
      <!-- Library Font Size Knob (CH 16 CC) -->
      <control>
        <group>[Library]</group>
        <key>VDJC.libraryFontSizeKnob</key>
        <status>0xBF</status>
        <midino>0x12</midino>
        <options>
          <Script-Binding/>
        </options>
      </control>
      <!-- Library Show Maximized (CH 16 CC) -->
      <control>
        <group>[Skin]</group>
        <key>VDJC.showMaximizedLibrary</key>
        <status>0xBF</status>
        <midino>0x13</midino>
        <options>
          <Script-Binding/>
        </options>
      </control>
      <!-- Library Move Horizontal (CH 16 CC) -->
      <control>
        <group>[Library]</group>
        <key>VDJC.libraryMoveHorizontal</key>
        <status>0xBF</status>
        <midino>0x14</midino>
        <options>
          <Script-Binding/>
        </options>
      </control>
      <!-- Skin View - Toggle Effect Rack (CH 16 Note) -->
      <control>
        <group>[Skin]</group>
        <key>VDJC.toggleEffectRack</key>
        <status>0x9F</status>
        <midino>0x20</midino>
        <options>
          <Script-Binding/>
        </options>
      </control>
      <!-- Skin View - Toggle Samplers (CH 16 Note) -->
      <control>
        <group>[Skin]</group>
        <key>VDJC.toggleSamplers</key>
        <status>0x9F</status>
        <midino>0x21</midino>
        <options>
          <Script-Binding/>
        </options>
      </control>
      <!-- Skin View - Toggle Vinyl Control (CH 16 Note) -->
      <control>
        <group>[Skin]</group>
        <key>VDJC.toggleVinylControl</key>
        <status>0x9F</status>
        <midino>0x22</midino>
        <options>
          <Script-Binding/>
        </options>
      </control>
    </controls>
  </controller>
</MixxxControllerPreset>
